{"external_urls": {"spotify": "https://open.spotify.com/artist/0a85EJEd3a9RGM9ops09rZ"}, "followers": {"href": null, "total": 31321}, "genres": ["rockabilly", "psychobilly", "rock and roll"], "href": "https://api.spotify.com/v1/artists/0a85EJEd3a9RGM9ops09rZ", "id": "0a85EJEd3a9RGM9ops09rZ", "images": [{"url": "https://i.scdn.co/image/ab6761610000e5eba544a58d98fde8fc82e5f3a6", "height": 640, "width": 640}, {"url": "https://i.scdn.co/image/ab67616100005174a544a58d98fde8fc82e5f3a6", "height": 320, "width": 320}, {"url": "https://i.scdn.co/image/ab6761610000f178a544a58d98fde8fc82e5f3a6", "height": 160, "width": 160}], "name": "Billy Lee Riley", "popularity": 32, "type": "artist", "uri": "spotify:artist:0a85EJEd3a9RGM9ops09rZ"}