{"external_urls": {"spotify": "https://open.spotify.com/artist/0WbeGaye1H1KUdYWzYlTmk"}, "followers": {"href": null, "total": 195051}, "genres": ["g-funk", "west coast hip hop", "hyphy", "gangster rap", "old school hip hop"], "href": "https://api.spotify.com/v1/artists/0WbeGaye1H1KUdYWzYlTmk", "id": "0WbeGaye1H1KUdYWzYlTmk", "images": [{"url": "https://i.scdn.co/image/ab67616d0000b27340e152d8a1f20c7a607e45db", "height": 640, "width": 640}, {"url": "https://i.scdn.co/image/ab67616d00001e0240e152d8a1f20c7a607e45db", "height": 300, "width": 300}, {"url": "https://i.scdn.co/image/ab67616d0000485140e152d8a1f20c7a607e45db", "height": 64, "width": 64}], "name": "Dru Down", "popularity": 44, "type": "artist", "uri": "spotify:artist:0WbeGaye1H1KUdYWzYlTmk"}