{"external_urls": {"spotify": "https://open.spotify.com/artist/14VbTTVRZW6DtcaFU4cPO8"}, "followers": {"href": null, "total": 2881}, "genres": ["traditional country", "classic country"], "href": "https://api.spotify.com/v1/artists/14VbTTVRZW6DtcaFU4cPO8", "id": "14VbTTVRZW6DtcaFU4cPO8", "images": [{"url": "https://i.scdn.co/image/ab67616d0000b273cb84c33f9f9641dc4d24c4df", "height": 640, "width": 640}, {"url": "https://i.scdn.co/image/ab67616d00001e02cb84c33f9f9641dc4d24c4df", "height": 300, "width": 300}, {"url": "https://i.scdn.co/image/ab67616d00004851cb84c33f9f9641dc4d24c4df", "height": 64, "width": 64}], "name": "Walter Brennan", "popularity": 22, "type": "artist", "uri": "spotify:artist:14VbTTVRZW6DtcaFU4cPO8"}