{"external_urls": {"spotify": "https://open.spotify.com/artist/1dLWg6m8RRhizsdqJbhyj3"}, "followers": {"href": null, "total": 2037817}, "genres": ["glam metal", "hard rock", "glam rock"], "href": "https://api.spotify.com/v1/artists/1dLWg6m8RRhizsdqJbhyj3", "id": "1dLWg6m8RRhizsdqJbhyj3", "images": [{"url": "https://i.scdn.co/image/ab6761610000e5ebbcab7477da13322f44ece6f8", "height": 640, "width": 640}, {"url": "https://i.scdn.co/image/ab67616100005174bcab7477da13322f44ece6f8", "height": 320, "width": 320}, {"url": "https://i.scdn.co/image/ab6761610000f178bcab7477da13322f44ece6f8", "height": 160, "width": 160}], "name": "Quiet Riot", "popularity": 56, "type": "artist", "uri": "spotify:artist:1dLWg6m8RRhizsdqJbhyj3"}