{"external_urls": {"spotify": "https://open.spotify.com/artist/3Mcii5XWf6E0lrY3Uky4cA"}, "followers": {"href": null, "total": 10989030}, "genres": ["gangster rap", "west coast hip hop", "old school hip hop", "g-funk", "hip hop"], "href": "https://api.spotify.com/v1/artists/3Mcii5XWf6E0lrY3Uky4cA", "id": "3Mcii5XWf6E0lrY3Uky4cA", "images": [{"url": "https://i.scdn.co/image/ab6761610000e5eb650e79afafd00492e33d7b8c", "height": 640, "width": 640}, {"url": "https://i.scdn.co/image/ab67616100005174650e79afafd00492e33d7b8c", "height": 320, "width": 320}, {"url": "https://i.scdn.co/image/ab6761610000f178650e79afafd00492e33d7b8c", "height": 160, "width": 160}], "name": "Ice Cube", "popularity": 73, "type": "artist", "uri": "spotify:artist:3Mcii5XWf6E0lrY3Uky4cA"}