{"external_urls": {"spotify": "https://open.spotify.com/artist/4tzxCsdhR0IIUNyzwrag4C"}, "followers": {"href": null, "total": 165160}, "genres": ["g-funk", "west coast hip hop", "old school hip hop", "hyphy"], "href": "https://api.spotify.com/v1/artists/4tzxCsdhR0IIUNyzwrag4C", "id": "4tzxCsdhR0IIUNyzwrag4C", "images": [{"url": "https://i.scdn.co/image/ab6761610000e5eb38c92da8c467e446b8eecd5b", "height": 640, "width": 640}, {"url": "https://i.scdn.co/image/ab6761610000517438c92da8c467e446b8eecd5b", "height": 320, "width": 320}, {"url": "https://i.scdn.co/image/ab6761610000f17838c92da8c467e446b8eecd5b", "height": 160, "width": 160}], "name": "Rappin' 4-Tay", "popularity": 51, "type": "artist", "uri": "spotify:artist:4tzxCsdhR0IIUNyzwrag4C"}