{"external_urls": {"spotify": "https://open.spotify.com/artist/5exO2eW84QucBhrRhcK76x"}, "followers": {"href": null, "total": 111540}, "genres": ["native american music", "folk rock", "folk"], "href": "https://api.spotify.com/v1/artists/5exO2eW84QucBhrRhcK76x", "id": "5exO2eW84QucBhrRhcK76x", "images": [{"url": "https://i.scdn.co/image/ab6761610000e5eb76bf720220b09ebcf3004d80", "height": 640, "width": 640}, {"url": "https://i.scdn.co/image/ab6761610000517476bf720220b09ebcf3004d80", "height": 320, "width": 320}, {"url": "https://i.scdn.co/image/ab6761610000f17876bf720220b09ebcf3004d80", "height": 160, "width": 160}], "name": "Buffy Sainte-Marie", "popularity": 38, "type": "artist", "uri": "spotify:artist:5exO2eW84QucBhrRhcK76x"}