{"external_urls": {"spotify": "https://open.spotify.com/artist/5HPsVk1MblCoa44WLJsQwN"}, "followers": {"href": null, "total": 86828}, "genres": ["freestyle", "funk melody", "miami bass", "latin hip hop", "chicago house"], "href": "https://api.spotify.com/v1/artists/5HPsVk1MblCoa44WLJsQwN", "id": "5HPsVk1MblCoa44WLJsQwN", "images": [{"url": "https://i.scdn.co/image/ab6761610000e5eb31c81bf132d17cde80daec3e", "height": 640, "width": 640}, {"url": "https://i.scdn.co/image/ab6761610000517431c81bf132d17cde80daec3e", "height": 320, "width": 320}, {"url": "https://i.scdn.co/image/ab6761610000f17831c81bf132d17cde80daec3e", "height": 160, "width": 160}], "name": "Lil Suzy", "popularity": 44, "type": "artist", "uri": "spotify:artist:5HPsVk1MblCoa44WLJsQwN"}