{"external_urls": {"spotify": "https://open.spotify.com/artist/5HRSYURV6LFFRCjAtiK0py"}, "followers": {"href": null, "total": 83586}, "genres": ["philly soul", "classic soul", "northern soul", "soul"], "href": "https://api.spotify.com/v1/artists/5HRSYURV6LFFRCjAtiK0py", "id": "5HRSYURV6LFFRCjAtiK0py", "images": [{"url": "https://i.scdn.co/image/98b31da2186c6b6a2e0cdd726b052042718f97b6", "height": 260, "width": 260}, {"url": "https://i.scdn.co/image/f809f9dbf8098ff10e38ddf36a1f5f91bf7fc8f5", "height": 200, "width": 200}, {"url": "https://i.scdn.co/image/ca090720a3cbee7ae81eda8097b246a5ed2ed39d", "height": 64, "width": 64}], "name": "Joe Simon", "popularity": 31, "type": "artist", "uri": "spotify:artist:5HRSYURV6LFFRCjAtiK0py"}