{"external_urls": {"spotify": "https://open.spotify.com/artist/6RhzdrHfuZEMnZTNRjbTpz"}, "followers": {"href": null, "total": 5150}, "genres": ["southern hip hop", "miami bass", "crunk"], "href": "https://api.spotify.com/v1/artists/6RhzdrHfuZEMnZTNRjbTpz", "id": "6RhzdrHfuZEMnZTNRjbTpz", "images": [{"url": "https://i.scdn.co/image/ab67616d0000b27348b5d2aca6c8d0074dc5b004", "height": 640, "width": 640}, {"url": "https://i.scdn.co/image/ab67616d00001e0248b5d2aca6c8d0074dc5b004", "height": 300, "width": 300}, {"url": "https://i.scdn.co/image/ab67616d0000485148b5d2aca6c8d0074dc5b004", "height": 64, "width": 64}], "name": "Hitman Sammy Sam", "popularity": 14, "type": "artist", "uri": "spotify:artist:6RhzdrHfuZEMnZTNRjbTpz"}