{"external_urls": {"spotify": "https://open.spotify.com/artist/6wU099wsnfSuP0lxWc0jgt"}, "followers": {"href": null, "total": 4885}, "genres": [], "href": "https://api.spotify.com/v1/artists/6wU099wsnfSuP0lxWc0jgt", "id": "6wU099wsnfSuP0lxWc0jgt", "images": [{"url": "https://i.scdn.co/image/ab6742d3000053b7324e91baa1cce0a6d63452dd", "height": 720, "width": 1280}, {"url": "https://i.scdn.co/image/ab6742d3000052b7324e91baa1cce0a6d63452dd", "height": 360, "width": 640}], "name": "Sly Fox", "popularity": 31, "type": "artist", "uri": "spotify:artist:6wU099wsnfSuP0lxWc0jgt"}