{"external_urls": {"spotify": "https://open.spotify.com/artist/7zeHJIIfNStVfxlbT72UwY"}, "followers": {"href": null, "total": 260190}, "genres": ["gothic rock", "darkwave", "post-punk", "deathrock", "new wave", "synthpop"], "href": "https://api.spotify.com/v1/artists/7zeHJIIfNStVfxlbT72UwY", "id": "7zeHJIIfNStVfxlbT72UwY", "images": [{"url": "https://i.scdn.co/image/ab6761610000e5eb835fb626c4e128712e731c83", "height": 640, "width": 640}, {"url": "https://i.scdn.co/image/ab67616100005174835fb626c4e128712e731c83", "height": 320, "width": 320}, {"url": "https://i.scdn.co/image/ab6761610000f178835fb626c4e128712e731c83", "height": 160, "width": 160}], "name": "Peter Murphy", "popularity": 43, "type": "artist", "uri": "spotify:artist:7zeHJIIfNStVfxlbT72UwY"}